{"\u6d77\u68e0\u7ecf\u96e8\u80ed\u8102\u900f": {"name": "\u51af\u6625\u8a00", "present": [0, 1, 0, 1, 6, 2, 2, 2, 9, 4, 2, 0, 0, 0, 0, 0, 0, 0, 2, 1, 7, 1, 2, 3, 5, 4, 2, 5, 6, 4, 2, 1, 7, 2, 0, 6, 4, 5, 3, 11, 7, 2, 2, 7, 2, 1, 5, 6, 7, 4, 0, 2], "time": "2019-10-24"}, "\u9648\u60c5\u4ee4": {"name": "\u84dd\u7ffc", "present": [0, 0, 0, 0, 0, 23, 11, 0, 0, 0, 0, 0, 0, 1, 0, 0, 0, 0, 0, 0, 0, 0, 0, 0, 0, 0, 0, 0, 0, 0, 0, 0, 0, 0, 0, 0, 0, 0, 0, 0, 0, 0, 0, 0, 0, 0, 0, 0, 0, 0], "time": "2019-06-27"}, "\u6597\u7834\u82cd\u7a79": {"name": "\u53e4\u6587\u5fc3", "present": [0, 0, 0, 5, 0, 0, 0, 0, 0, 0, 0, 0, 0, 0, 0, 1, 0, 0, 0, 3, 0, 0, 0, 0, 4, 0, 0, 0, 0, 1, 1, 0, 0, 0, 0, 0, 0, 0, 0, 0, 4, 0], "time": "2018-09-03"}, "\u5973\u4eba\u4ff1\u4e50\u90e8": {"name": "\u5deb\u5c0f\u8bd7\uff08\u4e2d\u5e74\uff09", "present": [0, 0, 0, 0, 0, 0, 0, 0, 0, 0, 0, 0, 0, 0, 0, 0, 0, 0, 0, 0, 0, 0, 0, 0, 0, 0, 0, 0, 0, 0, 0, 0], "time": "2014-04-21"}, "\u5927\u5b8b\u60ca\u4e16\u4f20\u5947": {"name": "\u5218\u5983", "present": [0, 2, 3, 6, 1, 4, 3, 0, 1, 1, 1, 3, 0, 0, 2, 7, 2, 3, 1, 1, 3, 1, 3, 1, 0, 1, 4, 2, 3, 3], "time": "2005"}, "\u6b66\u5f53": {"name": "\u6c88\u84c9", "present": [2, 0, 0, 1, 0, 0, 1, 3, 0, 0, 0, 0, 8, 0, 3, 2, 2, 1, 0, 2, 0, 0, 0, 0, 0, 0, 0, 1, 0, 1, 0, 0, 0, 0, 0, 0, 0, 0, 0, 0, 0, 0, 0, 0, 0, 0, 0, 0, 0, 0, 0, 0, 0, 0, 0, 0, 0, 0, 0, 0, 0, 0, 0, 0, 0, 0, 0, 0, 0, 0, 0, 0, 0, 0], "time": "2004"}, "\u5f52\u9014\u5982\u8679": {"name": "\u6797\u5609\u4eea", "present": [4, 2, 2, 2, 3, 1, 4, 3, 6, 2, 3, 2, 3, 6, 1, 0, 3, 4, 0, 2], "time": "2003-09-25"}, "\u79cb\u9999": {"name": "\u79cb\u9999", "present": [0, 0, 0, 0, 0, 1, 1, 1, 0, 0, 4, 2, 3, 5, 2, 0, 5, 2, 2, 3], "time": "2003"}, "\u5947\u4eba\u5947\u6848": {"name": "\u8bb8\u5982\u4fac", "present": [2, 1, 3, 0, 3, 0, 3, 1, 0, 1, 0, 2, 2, 1, 1, 3, 1, 0, 2, 1, 2, 3, 2, 3, 1, 0, 0, 2, 3, 0, 2, 1, 1, 2, 2], "time": "2001"}, "\u7f18\u6765\u4e00\u5bb6\u4eba": {"name": "\u8521\u5609", "present": [1, 0, 0, 0, 0, 0, 0, 0, 0, 0, 0, 0, 0, 0, 0, 0, 0, 0, 0, 0], "time": "2000"}, "\u5929\u9f99\u516b\u90e8": {"name": "\u738b\u8bed\u5ae3", "present": [0, 0, 0, 0, 0, 0, 1, 0, 0, 0, 0, 0, 0, 0, 0, 0, 0, 0, 0, 0, 0, 0, 0, 0, 0, 0, 0, 0, 0, 0, 0, 0, 0, 0, 0, 0, 0, 0, 0, 0], "time": "1997-07-28"}, "\u795e\u96d5\u4fa0\u4fa3": {"name": "\u5c0f\u9f99\u5973", "present": [0, 0, 0, 0, 1, 0, 0, 0, 0, 0, 1, 0, 1, 0, 0, 0, 0, 0, 0, 0, 0, 0, 0, 0, 0, 0, 0, 0, 0, 0, 0, 2], "time": "1995-07-31"}, "\u5ec9\u653f\u884c\u52a81994": {"name": "\u7f8e\u5b9d", "present": [0, 0, 0, 0, 0], "time": "1994"}}