{"": [], "\u65e9\u89c1\u4f26\u5b50": ["", "\u4f26\u5b50"], "\u5c3e\u82b1\u590f\u6811": ["\u5c3e\u82b1", "\u90a3\u4e2a\u7537\u4eba"], "\u4eac\u91ce": [], "\u6c5f\u85e4": [], "\u4e39\u540e": [], "\u76f8\u6cfd": [], "\u6c50\u6fd1": [], "\u4e45\u4f4f\u520a\u5948": ["", "\u520a\u5948"], "\u7433\u8fbe": [], "\u5cf0\u5cb8": [], "\u7965\u5e73": [], "\u840c\u7ed8": [], "\u7f8e\u4f18": [], "\u897f\u5802": [], "\u82b9\u7530": [], "\u827e\u4e3d\u4e9a": [], "\u7231\u7c73\u8389": [], "\u6f6e\u5353": [], "\u51ea\u5b50": [], "\u8d39\u5c14\u5357\u00b7\u6587\u5219\u00b7\u4f2f\u7eb3\u5c14": [], "\u7ed3\u6708": []}