{"\u9ea6\u745f\u5c14\u592b\u4eba": {"\u827e\u535a": 3, "\u7f57\u65af": 3, "\u82cf\u897f": 10, "\u4f0a\u83ab\u91d1": 2, "\u4e54\u5c14": 2}, "\u827e\u535a": {"\u9ea6\u745f\u5c14\u592b\u4eba": 3, "\u7f57\u65af": 8, "\u73cd\u59ae": 1}, "\u7f57\u65af": {"\u9ea6\u745f\u5c14\u592b\u4eba": 3, "\u827e\u535a": 8, "\u73cd\u59ae": 1}, "\u82cf\u897f": {"\u9ea6\u745f\u5c14\u592b\u4eba": 10, "\u4f0a\u83ab\u91d1": 1}, "\u4f0a\u83ab\u91d1": {"\u9ea6\u745f\u5c14\u592b\u4eba": 2, "\u82cf\u897f": 1, "\u4e54\u5c14": 1}, "\u4e54\u5c14": {"\u9ea6\u745f\u5c14\u592b\u4eba": 2, "\u4f0a\u83ab\u91d1": 1}, "\u73cd\u59ae": {"\u827e\u535a": 1, "\u7f57\u65af": 1}}